Divergence_Free_Interpolant/_Divergence_Free_interpolant.py
Divergence_Free_Interpolant/_Radial_Basis_Functions.py
Divergence_Free_Interpolant/__init__.py
Divergence_Free_Interpolant-0.1.6.dist-info/LICENSE
Divergence_Free_Interpolant-0.1.6.dist-info/METADATA
Divergence_Free_Interpolant-0.1.6.dist-info/WHEEL
Divergence_Free_Interpolant-0.1.6.dist-info/top_level.txt
Divergence_Free_Interpolant-0.1.6.dist-info/RECORD
