Metadata-Version: 2.1
Name: Divergence-Free-Interpolant
Version: 0.1.6
Summary: Divergence free interpolant for 2D and 3D systems
Home-page: https://github.com/Peteris-Zvejnieks/DivergenceFreeInterpolation
Author: Peteris Zvejnieks
Author-email: peterf610@gmail.com
License: MIT
Keywords: Interpolation Vector-Field Radial-Basis-Functions
Classifier: Programming Language :: Python :: 3
Classifier: License :: OSI Approved :: MIT License
Classifier: Operating System :: OS Independent
License-File: LICENSE
